react_select/ReactSelect.py
react_select/__init__.py
react_select_selenium-0.0.1.dist-info/LICENSE.txt
react_select_selenium-0.0.1.dist-info/METADATA
react_select_selenium-0.0.1.dist-info/WHEEL
react_select_selenium-0.0.1.dist-info/top_level.txt
react_select_selenium-0.0.1.dist-info/RECORD
