Metadata-Version: 2.1
Name: react-select-selenium
Version: 0.0.1
Summary: package for react select
Home-page: https://github.com/karins28/react-select-selenium
Author: Karin Shaim
Author-email: karins1010@gmail.com
License: UNKNOWN
Platform: UNKNOWN
Classifier: Programming Language :: Python :: 2.7
Classifier: License :: OSI Approved :: MIT License
Classifier: Operating System :: OS Independent
Requires-Dist: selenium
